odoo/addons/sale_default_uom/README.rst
odoo/addons/sale_default_uom/__init__.py
odoo/addons/sale_default_uom/__manifest__.py
odoo/addons/sale_default_uom/i18n/it.po
odoo/addons/sale_default_uom/i18n/sale_default_uom.pot
odoo/addons/sale_default_uom/models/__init__.py
odoo/addons/sale_default_uom/models/product_template.py
odoo/addons/sale_default_uom/models/sale_order_line.py
odoo/addons/sale_default_uom/readme/CONTRIBUTORS.rst
odoo/addons/sale_default_uom/readme/DESCRIPTION.rst
odoo/addons/sale_default_uom/readme/HISTORY.rst
odoo/addons/sale_default_uom/readme/USAGE.rst
odoo/addons/sale_default_uom/static/description/icon.png
odoo/addons/sale_default_uom/static/description/index.html
odoo/addons/sale_default_uom/tests/__init__.py
odoo/addons/sale_default_uom/tests/test_sale_order_line.py
odoo/addons/sale_default_uom/views/product_template_view.xml
odoo14_addon_sale_default_uom-14.0.1.1.1.dist-info/METADATA
odoo14_addon_sale_default_uom-14.0.1.1.1.dist-info/WHEEL
odoo14_addon_sale_default_uom-14.0.1.1.1.dist-info/top_level.txt
odoo14_addon_sale_default_uom-14.0.1.1.1.dist-info/RECORD
